tirreno_tracker/__init__.py
tirreno_tracker/tracking.py
tirreno_tracker-0.1.0b4.dist-info/licenses/LICENSE
tirreno_tracker-0.1.0b4.dist-info/METADATA
tirreno_tracker-0.1.0b4.dist-info/WHEEL
tirreno_tracker-0.1.0b4.dist-info/top_level.txt
tirreno_tracker-0.1.0b4.dist-info/RECORD
