Metadata-Version: 2.4
Name: tirreno_tracker
Version: 0.1.0b4
Summary: Python client for tirreno security analytics API
Home-page: https://github.com/tirrenotechnologies/tirreno-python-tracker
Author: tirreno technologies sàrl
Author-email: team@tirreno.com
License: BSD-3-Clause
Project-URL: Homepage, https://www.tirreno.com
Project-URL: Source Code, https://github.com/tirrenotechnologies/tirreno-python-tracker
Keywords: tirreno,fraud-detection,audit-trail,analytics,monitoring,bot-detection,antispam,application-monitoring
Classifier: Environment :: Web Environment
Classifier: Intended Audience :: Developers
Classifier: Operating System :: OS Independent
Classifier: Programming Language :: Python
Classifier: Programming Language :: Python :: 3
Classifier: Programming Language :: Python :: 3.6
Classifier: Programming Language :: Python :: 3.7
Classifier: Programming Language :: Python :: 3.8
Classifier: Programming Language :: Python :: 3.9
Classifier: Programming Language :: Python :: 3.10
Classifier: Programming Language :: Python :: 3.11
Classifier: Programming Language :: Python :: 3.12
Classifier: Programming Language :: Python :: 3.13
Classifier: Programming Language :: Python :: 3.14
Requires-Python: >=3.6
License-File: LICENSE
Requires-Dist: requests>=2
Requires-Dist: typing_extensions<4.2; python_version == "3.6"
Requires-Dist: typing_extensions<4.8; python_version == "3.7"
Requires-Dist: typing_extensions<4.14; python_version == "3.8"
Requires-Dist: importlib_metadata<=4.5; python_version == "3.6"
Requires-Dist: importlib_metadata<=7.0; python_version < "3.8"
Dynamic: author
Dynamic: author-email
Dynamic: classifier
Dynamic: description
Dynamic: description-content-type
Dynamic: home-page
Dynamic: keywords
Dynamic: license
Dynamic: license-file
Dynamic: project-url
Dynamic: requires-dist
Dynamic: requires-python
Dynamic: summary
